fouriercrop/__init__.py
fouriercrop/cli.py
fouriercrop/fouriercrop.py
fouriercrop/gui/__init__.py
fouriercrop/gui/main_window.py
fouriercrop/gui/resources/color.json
fouriercrop/gui/resources/logo.png
fouriercrop/py.typed
fouriercrop-2.0.0.dist-info/LICENSE.rst
fouriercrop-2.0.0.dist-info/METADATA
fouriercrop-2.0.0.dist-info/WHEEL
fouriercrop-2.0.0.dist-info/entry_points.txt
fouriercrop-2.0.0.dist-info/RECORD
