Metadata-Version: 2.3
Name: fouriercrop
Version: 2.0.0
Summary: FourierCrop is a Python package that enables downsampling and other operations using Fourier domain cropping techniques. These operations can be used for tasks like reducing resolution or resizing while maintaining spatial coherence.
Keywords: fouriercrop
Author: cryoetools
Author-email: cryoetools@outlook.com
Requires-Python: >=3.9,<3.11
Classifier: Development Status :: 2 - Pre-Alpha
Classifier: Intended Audience :: Developers
Classifier: License :: OSI Approved :: Apache Software License
Classifier: Natural Language :: English
Classifier: Programming Language :: Python :: 3
Classifier: Programming Language :: Python :: 3.9
Classifier: Programming Language :: Python :: 3.10
Requires-Dist: customtkinter (>=5.2.2,<6.0.0)
Requires-Dist: mrcfile (>=1.5.4,<2.0.0)
Requires-Dist: numpy (==1.25.0)
Requires-Dist: pillow (>=11.1.0,<12.0.0)
Requires-Dist: pydata-sphinx-theme (>=0.16.1,<0.17.0)
Requires-Dist: torch (==2.1.2)
Requires-Dist: typer[all] (>=0.13.0,<0.14.0)
Project-URL: Bug Tracker, https://github.com/cryoetools/fouriercrop/issues
Project-URL: Documentation, https://fouriercrop.readthedocs.io
Project-URL: Homepage, https://github.com/cryoetools/fouriercrop
Project-URL: Repository, https://github.com/cryoetools/fouriercrop
